roblox_requests/__init__.py
roblox_requests/__main__.py
roblox_requests/base.py
roblox_requests/cli.py
roblox_requests-3.0.0.dist-info/LICENSE
roblox_requests-3.0.0.dist-info/METADATA
roblox_requests-3.0.0.dist-info/WHEEL
roblox_requests-3.0.0.dist-info/entry_points.txt
roblox_requests-3.0.0.dist-info/top_level.txt
roblox_requests-3.0.0.dist-info/RECORD
