Metadata-Version: 2.1
Name: roblox_requests
Version: 3.0.0
Summary: Use easier requests for roblox.
Home-page: https://github.com
Author: author_name
License-File: LICENSE
Requires-Dist: requests
